sp_variant/__init__.py
sp_variant/__main__.py
sp_variant/defs.py
sp_variant/py.typed
sp_variant/variant.py
sp_variant/vbuild.py
sp_variant/yaiparser.py
sp_variant-3.5.3.dist-info/METADATA
sp_variant-3.5.3.dist-info/WHEEL
sp_variant-3.5.3.dist-info/entry_points.txt
sp_variant-3.5.3.dist-info/RECORD
